<annotation>
	<folder></folder>
	<filename>000054_JPG_jpg.rf.5a9fd3d99cea062cc1f374e32f713f54.jpg</filename>
	<path>000054_JPG_jpg.rf.5a9fd3d99cea062cc1f374e32f713f54.jpg</path>
	<source>
		<database>roboflow.ai</database>
	</source>
	<size>
		<width>448</width>
		<height>448</height>
		<depth>3</depth>
	</size>
	<segmented>0</segmented>
	<object>
		<name>Plastic container</name>
		<pose>Unspecified</pose>
		<truncated>0</truncated>
		<difficult>0</difficult>
		<occluded>0</occluded>
		<bndbox>
			<xmin>192</xmin>
			<xmax>321</xmax>
			<ymin>181</ymin>
			<ymax>238</ymax>
		</bndbox>
	</object>
</annotation>
