<annotation>
	<folder></folder>
	<filename>000095_jpg.rf.c8b234bab520c4def42ea60d2bfd805b.jpg</filename>
	<path>000095_jpg.rf.c8b234bab520c4def42ea60d2bfd805b.jpg</path>
	<source>
		<database>roboflow.ai</database>
	</source>
	<size>
		<width>448</width>
		<height>448</height>
		<depth>3</depth>
	</size>
	<segmented>0</segmented>
	<object>
		<name>Carton</name>
		<pose>Unspecified</pose>
		<truncated>0</truncated>
		<difficult>0</difficult>
		<occluded>0</occluded>
		<bndbox>
			<xmin>320</xmin>
			<xmax>337</xmax>
			<ymin>245</ymin>
			<ymax>295</ymax>
		</bndbox>
	</object>
	<object>
		<name>Carton</name>
		<pose>Unspecified</pose>
		<truncated>0</truncated>
		<difficult>0</difficult>
		<occluded>0</occluded>
		<bndbox>
			<xmin>250</xmin>
			<xmax>275</xmax>
			<ymin>213</ymin>
			<ymax>259</ymax>
		</bndbox>
	</object>
	<object>
		<name>Straw</name>
		<pose>Unspecified</pose>
		<truncated>0</truncated>
		<difficult>0</difficult>
		<occluded>0</occluded>
		<bndbox>
			<xmin>273</xmin>
			<xmax>279</xmax>
			<ymin>218</ymin>
			<ymax>225</ymax>
		</bndbox>
	</object>
	<object>
		<name>Unlabeled litter</name>
		<pose>Unspecified</pose>
		<truncated>0</truncated>
		<difficult>0</difficult>
		<occluded>0</occluded>
		<bndbox>
			<xmin>282</xmin>
			<xmax>288</xmax>
			<ymin>108</ymin>
			<ymax>127</ymax>
		</bndbox>
	</object>
	<object>
		<name>Unlabeled litter</name>
		<pose>Unspecified</pose>
		<truncated>0</truncated>
		<difficult>0</difficult>
		<occluded>0</occluded>
		<bndbox>
			<xmin>232</xmin>
			<xmax>242</xmax>
			<ymin>99</ymin>
			<ymax>142</ymax>
		</bndbox>
	</object>
	<object>
		<name>Plastic bag - wrapper</name>
		<pose>Unspecified</pose>
		<truncated>0</truncated>
		<difficult>0</difficult>
		<occluded>0</occluded>
		<bndbox>
			<xmin>128</xmin>
			<xmax>138</xmax>
			<ymin>48</ymin>
			<ymax>84</ymax>
		</bndbox>
	</object>
	<object>
		<name>Plastic bag - wrapper</name>
		<pose>Unspecified</pose>
		<truncated>0</truncated>
		<difficult>0</difficult>
		<occluded>0</occluded>
		<bndbox>
			<xmin>19</xmin>
			<xmax>38</xmax>
			<ymin>136</ymin>
			<ymax>156</ymax>
		</bndbox>
	</object>
	<object>
		<name>Unlabeled litter</name>
		<pose>Unspecified</pose>
		<truncated>0</truncated>
		<difficult>0</difficult>
		<occluded>0</occluded>
		<bndbox>
			<xmin>16</xmin>
			<xmax>34</xmax>
			<ymin>152</ymin>
			<ymax>175</ymax>
		</bndbox>
	</object>
	<object>
		<name>Unlabeled litter</name>
		<pose>Unspecified</pose>
		<truncated>0</truncated>
		<difficult>0</difficult>
		<occluded>0</occluded>
		<bndbox>
			<xmin>310</xmin>
			<xmax>319</xmax>
			<ymin>257</ymin>
			<ymax>288</ymax>
		</bndbox>
	</object>
</annotation>
