<annotation>
	<folder></folder>
	<filename>000014_JPG_jpg.rf.83f518fa18c4f5c22d7bbe1295ee7603.jpg</filename>
	<path>000014_JPG_jpg.rf.83f518fa18c4f5c22d7bbe1295ee7603.jpg</path>
	<source>
		<database>roboflow.ai</database>
	</source>
	<size>
		<width>448</width>
		<height>448</height>
		<depth>3</depth>
	</size>
	<segmented>0</segmented>
	<object>
		<name>Bottle</name>
		<pose>Unspecified</pose>
		<truncated>0</truncated>
		<difficult>0</difficult>
		<occluded>0</occluded>
		<bndbox>
			<xmin>182</xmin>
			<xmax>220</xmax>
			<ymin>272</ymin>
			<ymax>318</ymax>
		</bndbox>
	</object>
	<object>
		<name>Cigarette</name>
		<pose>Unspecified</pose>
		<truncated>0</truncated>
		<difficult>0</difficult>
		<occluded>0</occluded>
		<bndbox>
			<xmin>206</xmin>
			<xmax>210</xmax>
			<ymin>307</ymin>
			<ymax>311</ymax>
		</bndbox>
	</object>
	<object>
		<name>Cigarette</name>
		<pose>Unspecified</pose>
		<truncated>0</truncated>
		<difficult>0</difficult>
		<occluded>0</occluded>
		<bndbox>
			<xmin>196</xmin>
			<xmax>202</xmax>
			<ymin>335</ymin>
			<ymax>341</ymax>
		</bndbox>
	</object>
	<object>
		<name>Cigarette</name>
		<pose>Unspecified</pose>
		<truncated>0</truncated>
		<difficult>0</difficult>
		<occluded>0</occluded>
		<bndbox>
			<xmin>246</xmin>
			<xmax>252</xmax>
			<ymin>193</ymin>
			<ymax>204</ymax>
		</bndbox>
	</object>
	<object>
		<name>Cigarette</name>
		<pose>Unspecified</pose>
		<truncated>0</truncated>
		<difficult>0</difficult>
		<occluded>0</occluded>
		<bndbox>
			<xmin>303</xmin>
			<xmax>307</xmax>
			<ymin>183</ymin>
			<ymax>193</ymax>
		</bndbox>
	</object>
	<object>
		<name>Cigarette</name>
		<pose>Unspecified</pose>
		<truncated>0</truncated>
		<difficult>0</difficult>
		<occluded>0</occluded>
		<bndbox>
			<xmin>304</xmin>
			<xmax>311</xmax>
			<ymin>135</ymin>
			<ymax>143</ymax>
		</bndbox>
	</object>
	<object>
		<name>Cigarette</name>
		<pose>Unspecified</pose>
		<truncated>0</truncated>
		<difficult>0</difficult>
		<occluded>0</occluded>
		<bndbox>
			<xmin>323</xmin>
			<xmax>331</xmax>
			<ymin>376</ymin>
			<ymax>388</ymax>
		</bndbox>
	</object>
</annotation>
