<annotation>
	<folder></folder>
	<filename>IMG_5068_JPG_jpg.rf.12118ac8a734d1d8870a8077b43beb18.jpg</filename>
	<path>IMG_5068_JPG_jpg.rf.12118ac8a734d1d8870a8077b43beb18.jpg</path>
	<source>
		<database>roboflow.ai</database>
	</source>
	<size>
		<width>448</width>
		<height>448</height>
		<depth>3</depth>
	</size>
	<segmented>0</segmented>
	<object>
		<name>Paper</name>
		<pose>Unspecified</pose>
		<truncated>0</truncated>
		<difficult>0</difficult>
		<occluded>0</occluded>
		<bndbox>
			<xmin>37</xmin>
			<xmax>137</xmax>
			<ymin>329</ymin>
			<ymax>435</ymax>
		</bndbox>
	</object>
	<object>
		<name>Paper</name>
		<pose>Unspecified</pose>
		<truncated>0</truncated>
		<difficult>0</difficult>
		<occluded>0</occluded>
		<bndbox>
			<xmin>68</xmin>
			<xmax>130</xmax>
			<ymin>262</ymin>
			<ymax>319</ymax>
		</bndbox>
	</object>
	<object>
		<name>Paper</name>
		<pose>Unspecified</pose>
		<truncated>0</truncated>
		<difficult>0</difficult>
		<occluded>0</occluded>
		<bndbox>
			<xmin>60</xmin>
			<xmax>115</xmax>
			<ymin>224</ymin>
			<ymax>287</ymax>
		</bndbox>
	</object>
	<object>
		<name>Paper</name>
		<pose>Unspecified</pose>
		<truncated>0</truncated>
		<difficult>0</difficult>
		<occluded>0</occluded>
		<bndbox>
			<xmin>72</xmin>
			<xmax>143</xmax>
			<ymin>126</ymin>
			<ymax>229</ymax>
		</bndbox>
	</object>
	<object>
		<name>Paper</name>
		<pose>Unspecified</pose>
		<truncated>0</truncated>
		<difficult>0</difficult>
		<occluded>0</occluded>
		<bndbox>
			<xmin>116</xmin>
			<xmax>187</xmax>
			<ymin>160</ymin>
			<ymax>266</ymax>
		</bndbox>
	</object>
	<object>
		<name>Paper</name>
		<pose>Unspecified</pose>
		<truncated>0</truncated>
		<difficult>0</difficult>
		<occluded>0</occluded>
		<bndbox>
			<xmin>142</xmin>
			<xmax>230</xmax>
			<ymin>178</ymin>
			<ymax>257</ymax>
		</bndbox>
	</object>
	<object>
		<name>Paper</name>
		<pose>Unspecified</pose>
		<truncated>0</truncated>
		<difficult>0</difficult>
		<occluded>0</occluded>
		<bndbox>
			<xmin>121</xmin>
			<xmax>254</xmax>
			<ymin>221</ymin>
			<ymax>425</ymax>
		</bndbox>
	</object>
</annotation>
